{
  "project_info": {
    "project_number": "1043426563114",
    "firebase_url": "https://ibet-142013.firebaseio.com",
    "project_id": "ibet-142013",
    "storage_bucket": "ibet-142013.appspot.com"
  },
  "client": [
    {
      "client_info": {
        "mobilesdk_app_id": "1:1043426563114:android:ade0d4e8a88565c3",
        "android_client_info": {
          "package_name": "com.netforceinfotech.ibet"
        }
      },
      "oauth_client": [
        {
          "client_id": "1043426563114-7bubo07a6t7n9pmq7nqulhv1qkdkt9u5.apps.googleusercontent.com",
          "client_type": 1,
          "android_info": {
            "package_name": "com.netforceinfotech.ibet",
            "certificate_hash": "48C99B97A3C86D24F9C39063EC52509DD0741CD0"
          }
        },
        {
          "client_id": "1043426563114-ihnbnps95dpv1dc0gvo6uaeuha4qse2v.apps.googleusercontent.com",
          "client_type": 3
        }
      ],
      "api_key": [
        {
          "current_key": "AIzaSyD49GBWIlLpTnV_6_3LULpeCj0aOK7O4y4"
        }
      ],
      "services": {
        "analytics_service": {
          "status": 1
        },
        "appinvite_service": {
          "status": 2,
          "other_platform_oauth_client": [
            {
              "client_id": "1043426563114-ihnbnps95dpv1dc0gvo6uaeuha4qse2v.apps.googleusercontent.com",
              "client_type": 3
            }
          ]
        },
        "ads_service": {
          "status": 2
        }
      }
    }
  ],
  "configuration_version": "1"
}